fiducia/__init__.py
fiducia/cspline.py
fiducia/error.py
fiducia/loader.py
fiducia/main.py
fiducia/misc.py
fiducia/pltDefaults.py
fiducia/rawProcess.py
fiducia/response.py
fiducia/stats.py
fiducia/visualization.py
fiducia-0.2.dist-info/LICENSE.md
fiducia-0.2.dist-info/METADATA
fiducia-0.2.dist-info/WHEEL
fiducia-0.2.dist-info/top_level.txt
fiducia-0.2.dist-info/zip-safe
fiducia-0.2.dist-info/RECORD
