Metadata-Version: 2.1
Name: fiducia
Version: 0.2
Summary: DANTE data unfolder using cubic-spline algorithm
Home-page: https://github.com/lanl/fiducia
Author: Pawel M. Kozlowski, et al.
Author-email: pkozlowski@lanl.gov
License: BSD
Platform: UNKNOWN
